resume_pkg/__init__.py
resume_pkg/main.py
subham_resume-0.1.0.dist-info/METADATA
subham_resume-0.1.0.dist-info/WHEEL
subham_resume-0.1.0.dist-info/entry_points.txt
subham_resume-0.1.0.dist-info/top_level.txt
subham_resume-0.1.0.dist-info/RECORD
