Metadata-Version: 2.4
Name: subham-resume
Version: 0.1.0
Summary: Subham's resume as a pip package
Author: Subham Ghosh
